{"webPage":{"url":"https://support.google.com/","id":"Google_Support_Page","environment":"LP","displayName":"Google Support Home Page ","description":"Sample Description"},"webApplication":{"id":"google.com","name":"google.com","version":"1.0.0","gitRepoUrl":"","gitBranchName":"master"},"auditInstanceId":"024fe617-b0e8-4e02-9fab-1affa082202b","startDateTime":"2023-06-01T08:25:31.112Z","endDateTime":"2023-06-01T08:26:00.298Z","networkThrottle":{"rttMs":100,"throughputKbps":5500},"cpuSlowDownMultiplier":1,"loadTimeInteractive":1205.361,"loadTimeSpeedIndex":1300}