{"webPage":{"url":"https://wwwtest.fedex.com/magr/app/index.html","id":"MAGR_LANDING_PAGE","environment":"L6","displayName":"MAGR LANDING PAGE","description":"MAGR APP LANDING PAGE"},"webApplication":{"id":"MAGR","name":"Magic-Rating","version":"2.5.4","gitRepoUrl":"","gitBranchName":"master"},"throttledAuditGroupId":"15c4f20d-a8e6-4023-92c9-143985b71984","startDateTime":"2023-06-02T02:30:08.480Z","endDateTime":"2023-06-02T02:30:40.107Z","networkThrottle":{"rttMs":100,"throughputKbps":15500},"cpuSlowDownMultiplier":1,"loadTimeInteractive":8764.502,"loadTimeSpeedIndex":5494}