{"webPage":{"url":"https://wwwtest.fedex.com/magr/app/index.html","id":"MAGR_LANDING_PAGE","environment":"L6","displayName":"MAGR LANDING PAGE","description":"MAGR APP LANDING PAGE"},"webApplication":{"id":"MAGR","name":"Magic-Rating","version":"2.5.4","gitRepoUrl":"","gitBranchName":"master"},"throttledAuditGroupId":"a8f2ce38-77a6-436e-922b-814ab3a45dbf","startDateTime":"2023-06-02T03:30:21.088Z","endDateTime":"2023-06-02T03:30:57.326Z","networkThrottle":{"rttMs":100,"throughputKbps":5500},"cpuSlowDownMultiplier":0,"loadTimeInteractive":14511.754,"loadTimeSpeedIndex":10021}