{"webPage":{"url":"https://support.google.com/","id":"Google_Support_Page","environment":"LP","displayName":"Google Support Home Page ","description":"Sample Description"},"webApplication":{"id":"google.com","name":"google.com","version":"1.0.0","gitRepoUrl":"","gitBranchName":"master"},"cpuSlowDownMultiplier":2,"networkSpeed":25500,"labels":["2023-06-01T08:33:42.944Z-024fe617-b0e8-4e02-9fab-1affa082202b","2023-06-01T09:18:45.454Z-3f7e5856-465e-4c2e-a5ef-88d1a79dab7e","2023-06-01T08:44:50.665Z-75f6497e-e4c0-45b1-9791-aaca923e3882","2023-06-01T08:56:07.575Z-8e8a695e-d047-4c93-8196-715a6edeca3d","2023-06-01T09:07:31.816Z-b35ce195-4ec0-4f98-8243-4e3943778d24"],"listOfDataSets":{"interactive":[1536.079,1710.206,1497.798,1520.679,1667.984],"speedindex":[1074,1190,1043,1043,1151]}}