[{"appInfo":{"projectName":"AppName","version":"0.0.1","gitRepoUrl":"https://github.com/repo","gitBranchName":"main","initiatedBy":"performance folder"},"sessionId":"66cc29d2-3f43-47b9-a910-9de3da1470ec","initiatedBy":"performance folder","executionEnvironment":"env-to-be-filled-in","startDateTime":"2023-05-25T15:55:58.236Z","endDateTime":"2023-05-25T16:01:02.920Z","networkThrottle":10000,"cpuSlowDownMultiplier":1,"loadTimeInteractive":710.3530000305176,"loadTimeSpeedIndex":711},{"appInfo":{"projectName":"AppName","version":"0.0.1","gitRepoUrl":"https://github.com/repo","gitBranchName":"main","initiatedBy":"performance folder"},"sessionId":"66cc29d2-3f43-47b9-a910-9de3da1470ec","initiatedBy":"performance folder","executionEnvironment":"env-to-be-filled-in","startDateTime":"2023-05-25T15:53:53.344Z","endDateTime":"2023-05-25T16:01:02.923Z","networkThrottle":1500,"cpuSlowDownMultiplier":1,"loadTimeInteractive":1268.6819999694824,"loadTimeSpeedIndex":1220},{"appInfo":{"projectName":"AppName","version":"0.0.1","gitRepoUrl":"https://github.com/repo","gitBranchName":"main","initiatedBy":"performance folder"},"sessionId":"66cc29d2-3f43-47b9-a910-9de3da1470ec","initiatedBy":"performance folder","executionEnvironment":"env-to-be-filled-in","startDateTime":"2023-05-25T15:56:38.965Z","endDateTime":"2023-05-25T16:01:02.925Z","networkThrottle":20000,"cpuSlowDownMultiplier":1,"loadTimeInteractive":662.0510000305176,"loadTimeSpeedIndex":665},{"appInfo":{"projectName":"AppName","version":"0.0.1","gitRepoUrl":"https://github.com/repo","gitBranchName":"main","initiatedBy":"performance folder"},"sessionId":"66cc29d2-3f43-47b9-a910-9de3da1470ec","initiatedBy":"performance folder","executionEnvironment":"env-to-be-filled-in","startDateTime":"2023-05-25T15:57:19.512Z","endDateTime":"2023-05-25T16:01:02.927Z","networkThrottle":22500,"cpuSlowDownMultiplier":1,"loadTimeInteractive":700.882,"loadTimeSpeedIndex":706},{"appInfo":{"projectName":"AppName","version":"0.0.1","gitRepoUrl":"https://github.com/repo","gitBranchName":"main","initiatedBy":"performance folder"},"sessionId":"66cc29d2-3f43-47b9-a910-9de3da1470ec","initiatedBy":"performance folder","executionEnvironment":"env-to-be-filled-in","startDateTime":"2023-05-25T15:54:36.593Z","endDateTime":"2023-05-25T16:01:02.932Z","networkThrottle":2500,"cpuSlowDownMultiplier":1,"loadTimeInteractive":782.21,"loadTimeSpeedIndex":775},{"appInfo":{"projectName":"AppName","version":"0.0.1","gitRepoUrl":"https://github.com/repo","gitBranchName":"main","initiatedBy":"performance folder"},"sessionId":"66cc29d2-3f43-47b9-a910-9de3da1470ec","initiatedBy":"performance folder","executionEnvironment":"env-to-be-filled-in","startDateTime":"2023-05-25T15:58:00.045Z","endDateTime":"2023-05-25T16:01:02.934Z","networkThrottle":25000,"cpuSlowDownMultiplier":1,"loadTimeInteractive":804.9900000305175,"loadTimeSpeedIndex":801},{"appInfo":{"projectName":"AppName","version":"0.0.1","gitRepoUrl":"https://github.com/repo","gitBranchName":"main","initiatedBy":"performance folder"},"sessionId":"66cc29d2-3f43-47b9-a910-9de3da1470ec","initiatedBy":"performance folder","executionEnvironment":"env-to-be-filled-in","startDateTime":"2023-05-25T15:58:40.841Z","endDateTime":"2023-05-25T16:01:02.936Z","networkThrottle":27500,"cpuSlowDownMultiplier":1,"loadTimeInteractive":671.1440000305175,"loadTimeSpeedIndex":678},{"appInfo":{"projectName":"AppName","version":"0.0.1","gitRepoUrl":"https://github.com/repo","gitBranchName":"main","initiatedBy":"performance folder"},"sessionId":"66cc29d2-3f43-47b9-a910-9de3da1470ec","initiatedBy":"performance folder","executionEnvironment":"env-to-be-filled-in","startDateTime":"2023-05-25T15:59:21.481Z","endDateTime":"2023-05-25T16:01:02.938Z","networkThrottle":28000,"cpuSlowDownMultiplier":1,"loadTimeInteractive":670.413,"loadTimeSpeedIndex":685},{"appInfo":{"projectName":"AppName","version":"0.0.1","gitRepoUrl":"https://github.com/repo","gitBranchName":"main","initiatedBy":"performance folder"},"sessionId":"66cc29d2-3f43-47b9-a910-9de3da1470ec","initiatedBy":"performance folder","executionEnvironment":"env-to-be-filled-in","startDateTime":"2023-05-25T16:00:01.887Z","endDateTime":"2023-05-25T16:01:02.940Z","networkThrottle":29000,"cpuSlowDownMultiplier":1,"loadTimeInteractive":670.6379999694824,"loadTimeSpeedIndex":677},{"appInfo":{"projectName":"AppName","version":"0.0.1","gitRepoUrl":"https://github.com/repo","gitBranchName":"main","initiatedBy":"performance folder"},"sessionId":"66cc29d2-3f43-47b9-a910-9de3da1470ec","initiatedBy":"performance folder","executionEnvironment":"env-to-be-filled-in","startDateTime":"2023-05-25T16:00:44.355Z","endDateTime":"2023-05-25T16:01:02.942Z","networkThrottle":29500,"cpuSlowDownMultiplier":1,"loadTimeInteractive":690.203,"loadTimeSpeedIndex":699},{"appInfo":{"projectName":"AppName","version":"0.0.1","gitRepoUrl":"https://github.com/repo","gitBranchName":"main","initiatedBy":"performance folder"},"sessionId":"66cc29d2-3f43-47b9-a910-9de3da1470ec","initiatedBy":"performance folder","executionEnvironment":"env-to-be-filled-in","startDateTime":"2023-05-25T15:51:09.277Z","endDateTime":"2023-05-25T16:01:02.944Z","networkThrottle":30000,"cpuSlowDownMultiplier":1,"loadTimeInteractive":707.0059999694824,"loadTimeSpeedIndex":712},{"appInfo":{"projectName":"AppName","version":"0.0.1","gitRepoUrl":"https://github.com/repo","gitBranchName":"main","initiatedBy":"performance folder"},"sessionId":"66cc29d2-3f43-47b9-a910-9de3da1470ec","initiatedBy":"performance folder","executionEnvironment":"env-to-be-filled-in","startDateTime":"2023-05-25T15:51:51.014Z","endDateTime":"2023-05-25T16:01:02.947Z","networkThrottle":35000,"cpuSlowDownMultiplier":1,"loadTimeInteractive":668.821,"loadTimeSpeedIndex":673},{"appInfo":{"projectName":"AppName","version":"0.0.1","gitRepoUrl":"https://github.com/repo","gitBranchName":"main","initiatedBy":"performance folder"},"sessionId":"66cc29d2-3f43-47b9-a910-9de3da1470ec","initiatedBy":"performance folder","executionEnvironment":"env-to-be-filled-in","startDateTime":"2023-05-25T15:52:31.568Z","endDateTime":"2023-05-25T16:01:02.949Z","networkThrottle":40000,"cpuSlowDownMultiplier":1,"loadTimeInteractive":688.4549999694824,"loadTimeSpeedIndex":694},{"appInfo":{"projectName":"AppName","version":"0.0.1","gitRepoUrl":"https://github.com/repo","gitBranchName":"main","initiatedBy":"performance folder"},"sessionId":"66cc29d2-3f43-47b9-a910-9de3da1470ec","initiatedBy":"performance folder","executionEnvironment":"env-to-be-filled-in","startDateTime":"2023-05-25T15:53:12.135Z","endDateTime":"2023-05-25T16:01:02.951Z","networkThrottle":45000,"cpuSlowDownMultiplier":1,"loadTimeInteractive":656.243,"loadTimeSpeedIndex":662},{"appInfo":{"projectName":"AppName","version":"0.0.1","gitRepoUrl":"https://github.com/repo","gitBranchName":"main","initiatedBy":"performance folder"},"sessionId":"66cc29d2-3f43-47b9-a910-9de3da1470ec","initiatedBy":"performance folder","executionEnvironment":"env-to-be-filled-in","startDateTime":"2023-05-25T15:55:17.654Z","endDateTime":"2023-05-25T16:01:02.953Z","networkThrottle":5000,"cpuSlowDownMultiplier":1,"loadTimeInteractive":709.386,"loadTimeSpeedIndex":721},{"appInfo":{"projectName":"AppName","version":"0.0.1","gitRepoUrl":"https://github.com/repo","gitBranchName":"main","initiatedBy":"performance folder"},"sessionId":"66cc29d2-3f43-47b9-a910-9de3da1470ec","initiatedBy":"performance folder","executionEnvironment":"env-to-be-filled-in","startDateTime":"2023-05-25T15:55:38.127Z","endDateTime":"2023-05-25T16:01:02.955Z","networkThrottle":10000,"cpuSlowDownMultiplier":4,"loadTimeInteractive":1257.044,"loadTimeSpeedIndex":696},{"appInfo":{"projectName":"AppName","version":"0.0.1","gitRepoUrl":"https://github.com/repo","gitBranchName":"main","initiatedBy":"performance folder"},"sessionId":"66cc29d2-3f43-47b9-a910-9de3da1470ec","initiatedBy":"performance folder","executionEnvironment":"env-to-be-filled-in","startDateTime":"2023-05-25T15:53:32.591Z","endDateTime":"2023-05-25T16:01:02.957Z","networkThrottle":1500,"cpuSlowDownMultiplier":4,"loadTimeInteractive":865.6519999694824,"loadTimeSpeedIndex":836},{"appInfo":{"projectName":"AppName","version":"0.0.1","gitRepoUrl":"https://github.com/repo","gitBranchName":"main","initiatedBy":"performance folder"},"sessionId":"66cc29d2-3f43-47b9-a910-9de3da1470ec","initiatedBy":"performance folder","executionEnvironment":"env-to-be-filled-in","startDateTime":"2023-05-25T15:56:18.659Z","endDateTime":"2023-05-25T16:01:02.960Z","networkThrottle":20000,"cpuSlowDownMultiplier":4,"loadTimeInteractive":825.3009999694824,"loadTimeSpeedIndex":817},{"appInfo":{"projectName":"AppName","version":"0.0.1","gitRepoUrl":"https://github.com/repo","gitBranchName":"main","initiatedBy":"performance folder"},"sessionId":"66cc29d2-3f43-47b9-a910-9de3da1470ec","initiatedBy":"performance folder","executionEnvironment":"env-to-be-filled-in","startDateTime":"2023-05-25T15:56:59.437Z","endDateTime":"2023-05-25T16:01:02.962Z","networkThrottle":22500,"cpuSlowDownMultiplier":4,"loadTimeInteractive":688.777,"loadTimeSpeedIndex":672},{"appInfo":{"projectName":"AppName","version":"0.0.1","gitRepoUrl":"https://github.com/repo","gitBranchName":"main","initiatedBy":"performance folder"},"sessionId":"66cc29d2-3f43-47b9-a910-9de3da1470ec","initiatedBy":"performance folder","executionEnvironment":"env-to-be-filled-in","startDateTime":"2023-05-25T15:54:16.303Z","endDateTime":"2023-05-25T16:01:02.964Z","networkThrottle":2500,"cpuSlowDownMultiplier":4,"loadTimeInteractive":757.081,"loadTimeSpeedIndex":745},{"appInfo":{"projectName":"AppName","version":"0.0.1","gitRepoUrl":"https://github.com/repo","gitBranchName":"main","initiatedBy":"performance folder"},"sessionId":"66cc29d2-3f43-47b9-a910-9de3da1470ec","initiatedBy":"performance folder","executionEnvironment":"env-to-be-filled-in","startDateTime":"2023-05-25T15:57:39.985Z","endDateTime":"2023-05-25T16:01:02.966Z","networkThrottle":25000,"cpuSlowDownMultiplier":4,"loadTimeInteractive":679.2280000305176,"loadTimeSpeedIndex":659},{"appInfo":{"projectName":"AppName","version":"0.0.1","gitRepoUrl":"https://github.com/repo","gitBranchName":"main","initiatedBy":"performance folder"},"sessionId":"66cc29d2-3f43-47b9-a910-9de3da1470ec","initiatedBy":"performance folder","executionEnvironment":"env-to-be-filled-in","startDateTime":"2023-05-25T15:58:20.630Z","endDateTime":"2023-05-25T16:01:02.968Z","networkThrottle":27500,"cpuSlowDownMultiplier":4,"loadTimeInteractive":673.7209999694825,"loadTimeSpeedIndex":664},{"appInfo":{"projectName":"AppName","version":"0.0.1","gitRepoUrl":"https://github.com/repo","gitBranchName":"main","initiatedBy":"performance folder"},"sessionId":"66cc29d2-3f43-47b9-a910-9de3da1470ec","initiatedBy":"performance folder","executionEnvironment":"env-to-be-filled-in","startDateTime":"2023-05-25T15:59:01.248Z","endDateTime":"2023-05-25T16:01:02.973Z","networkThrottle":28000,"cpuSlowDownMultiplier":4,"loadTimeInteractive":830.227,"loadTimeSpeedIndex":816},{"appInfo":{"projectName":"AppName","version":"0.0.1","gitRepoUrl":"https://github.com/repo","gitBranchName":"main","initiatedBy":"performance folder"},"sessionId":"66cc29d2-3f43-47b9-a910-9de3da1470ec","initiatedBy":"performance folder","executionEnvironment":"env-to-be-filled-in","startDateTime":"2023-05-25T15:59:41.890Z","endDateTime":"2023-05-25T16:01:02.977Z","networkThrottle":29000,"cpuSlowDownMultiplier":4,"loadTimeInteractive":708.447,"loadTimeSpeedIndex":698},{"appInfo":{"projectName":"AppName","version":"0.0.1","gitRepoUrl":"https://github.com/repo","gitBranchName":"main","initiatedBy":"performance folder"},"sessionId":"66cc29d2-3f43-47b9-a910-9de3da1470ec","initiatedBy":"performance folder","executionEnvironment":"env-to-be-filled-in","startDateTime":"2023-05-25T16:00:22.516Z","endDateTime":"2023-05-25T16:01:02.980Z","networkThrottle":29500,"cpuSlowDownMultiplier":4,"loadTimeInteractive":738.209,"loadTimeSpeedIndex":731},{"appInfo":{"projectName":"AppName","version":"0.0.1","gitRepoUrl":"https://github.com/repo","gitBranchName":"main","initiatedBy":"performance folder"},"sessionId":"66cc29d2-3f43-47b9-a910-9de3da1470ec","initiatedBy":"performance folder","executionEnvironment":"env-to-be-filled-in","startDateTime":"2023-05-25T15:50:48.719Z","endDateTime":"2023-05-25T16:01:02.985Z","networkThrottle":30000,"cpuSlowDownMultiplier":4,"loadTimeInteractive":837.6529999694824,"loadTimeSpeedIndex":824},{"appInfo":{"projectName":"AppName","version":"0.0.1","gitRepoUrl":"https://github.com/repo","gitBranchName":"main","initiatedBy":"performance folder"},"sessionId":"66cc29d2-3f43-47b9-a910-9de3da1470ec","initiatedBy":"performance folder","executionEnvironment":"env-to-be-filled-in","startDateTime":"2023-05-25T15:51:30.987Z","endDateTime":"2023-05-25T16:01:02.988Z","networkThrottle":35000,"cpuSlowDownMultiplier":4,"loadTimeInteractive":681.616,"loadTimeSpeedIndex":672},{"appInfo":{"projectName":"AppName","version":"0.0.1","gitRepoUrl":"https://github.com/repo","gitBranchName":"main","initiatedBy":"performance folder"},"sessionId":"66cc29d2-3f43-47b9-a910-9de3da1470ec","initiatedBy":"performance folder","executionEnvironment":"env-to-be-filled-in","startDateTime":"2023-05-25T15:52:11.478Z","endDateTime":"2023-05-25T16:01:02.990Z","networkThrottle":40000,"cpuSlowDownMultiplier":4,"loadTimeInteractive":695.458,"loadTimeSpeedIndex":688},{"appInfo":{"projectName":"AppName","version":"0.0.1","gitRepoUrl":"https://github.com/repo","gitBranchName":"main","initiatedBy":"performance folder"},"sessionId":"66cc29d2-3f43-47b9-a910-9de3da1470ec","initiatedBy":"performance folder","executionEnvironment":"env-to-be-filled-in","startDateTime":"2023-05-25T15:52:52.006Z","endDateTime":"2023-05-25T16:01:02.992Z","networkThrottle":45000,"cpuSlowDownMultiplier":4,"loadTimeInteractive":719.697,"loadTimeSpeedIndex":703},{"appInfo":{"projectName":"AppName","version":"0.0.1","gitRepoUrl":"https://github.com/repo","gitBranchName":"main","initiatedBy":"performance folder"},"sessionId":"66cc29d2-3f43-47b9-a910-9de3da1470ec","initiatedBy":"performance folder","executionEnvironment":"env-to-be-filled-in","startDateTime":"2023-05-25T15:54:57.242Z","endDateTime":"2023-05-25T16:01:02.994Z","networkThrottle":5000,"cpuSlowDownMultiplier":4,"loadTimeInteractive":826.53,"loadTimeSpeedIndex":818}]